gcpds_cv_pykit/__init__.py
gcpds_cv_pykit/baseline/__init__.py
gcpds_cv_pykit/baseline/performance_model.py
gcpds_cv_pykit/baseline/dataloaders/__init__.py
gcpds_cv_pykit/baseline/dataloaders/dataloader.py
gcpds_cv_pykit/baseline/losses/CrossEntropy.py
gcpds_cv_pykit/baseline/losses/DICE.py
gcpds_cv_pykit/baseline/losses/Focal.py
gcpds_cv_pykit/baseline/losses/Tversky.py
gcpds_cv_pykit/baseline/losses/__init__.py
gcpds_cv_pykit/baseline/models/UNet.py
gcpds_cv_pykit/baseline/models/__init__.py
gcpds_cv_pykit/baseline/trainers/__init__.py
gcpds_cv_pykit/baseline/trainers/trainer.py
gcpds_cv_pykit-0.1.1.dist-info/LICENSE
gcpds_cv_pykit-0.1.1.dist-info/METADATA
gcpds_cv_pykit-0.1.1.dist-info/WHEEL
gcpds_cv_pykit-0.1.1.dist-info/entry_points.txt
gcpds_cv_pykit-0.1.1.dist-info/top_level.txt
gcpds_cv_pykit-0.1.1.dist-info/RECORD
