Metadata-Version: 2.1
Name: gcpds-cv-pykit
Version: 0.1.1
Summary: A comprehensive toolkit for computer vision and segmentation tasks
Home-page: https://github.com/UN-GCPDS/gcpds-cv-pykit
Author: GCPDS Team
Author-email: gcpds_man@unal.edu.co
Maintainer: GCPDS Team
Maintainer-email: gcpds_man@unal.edu.co
License: MIT
Project-URL: Bug Reports, https://github.com/UN-GCPDS/gcpds-cv-pykit/issues
Project-URL: Source, https://github.com/UN-GCPDS/gcpds-cv-pykit
Project-URL: Documentation, https://gcpds-cv-pykit.readthedocs.io/
Keywords: computer vision,segmentation,deep learning,pytorch,unet,medical imaging,image processing,machine learning,artificial intelligence
Platform: any
Classifier: Development Status :: 3 - Alpha
Classifier: Intended Audience :: Developers
Classifier: Intended Audience :: Science/Research
Classifier: Intended Audience :: Education
Classifier: License :: OSI Approved :: MIT License
Classifier: Operating System :: OS Independent
Classifier: Programming Language :: Python :: 3
Classifier: Programming Language :: Python :: 3.8
Classifier: Programming Language :: Python :: 3.9
Classifier: Programming Language :: Python :: 3.10
Classifier: Programming Language :: Python :: 3.11
Classifier: Programming Language :: Python :: 3.12
Classifier: Topic :: Scientific/Engineering :: Artificial Intelligence
Classifier: Topic :: Scientific/Engineering :: Image Processing
Classifier: Topic :: Software Development :: Libraries :: Python Modules
Requires-Python: >=3.8
License-File: LICENSE
Requires-Dist: torch>=2.0.0
Requires-Dist: torchvision>=0.15.0
Requires-Dist: numpy>=1.21.0
Requires-Dist: tqdm>=4.64.0
Requires-Dist: matplotlib>=3.5.0
Requires-Dist: wandb>=0.15.0
Requires-Dist: opencv-python>=4.6.0
Requires-Dist: Pillow>=9.0.0
Requires-Dist: scipy>=1.9.0
Requires-Dist: pandas>=1.4.0
Provides-Extra: all
Requires-Dist: pytest>=7.0.0; extra == "all"
Requires-Dist: pytest-cov>=4.0.0; extra == "all"
Requires-Dist: black>=22.0.0; extra == "all"
Requires-Dist: flake8>=5.0.0; extra == "all"
Requires-Dist: isort>=5.10.0; extra == "all"
Requires-Dist: pre-commit>=2.20.0; extra == "all"
Requires-Dist: sphinx>=5.0.0; extra == "all"
Requires-Dist: sphinx-rtd-theme>=1.0.0; extra == "all"
Requires-Dist: sphinx-autodoc-typehints>=1.19.0; extra == "all"
Requires-Dist: myst-parser>=0.18.0; extra == "all"
Requires-Dist: jupyter>=1.0.0; extra == "all"
Requires-Dist: ipywidgets>=8.0.0; extra == "all"
Requires-Dist: notebook>=6.4.0; extra == "all"
Provides-Extra: dev
Requires-Dist: pytest>=7.0.0; extra == "dev"
Requires-Dist: pytest-cov>=4.0.0; extra == "dev"
Requires-Dist: black>=22.0.0; extra == "dev"
Requires-Dist: flake8>=5.0.0; extra == "dev"
Requires-Dist: isort>=5.10.0; extra == "dev"
Requires-Dist: pre-commit>=2.20.0; extra == "dev"
Provides-Extra: docs
Requires-Dist: sphinx>=5.0.0; extra == "docs"
Requires-Dist: sphinx-rtd-theme>=1.0.0; extra == "docs"
Requires-Dist: sphinx-autodoc-typehints>=1.19.0; extra == "docs"
Requires-Dist: myst-parser>=0.18.0; extra == "docs"
Provides-Extra: jupyter
Requires-Dist: jupyter>=1.0.0; extra == "jupyter"
Requires-Dist: ipywidgets>=8.0.0; extra == "jupyter"
Requires-Dist: notebook>=6.4.0; extra == "jupyter"
